README.md
setup.py
TOPSIS_Akshit_101803487.egg-info/PKG-INFO
TOPSIS_Akshit_101803487.egg-info/SOURCES.txt
TOPSIS_Akshit_101803487.egg-info/dependency_links.txt
TOPSIS_Akshit_101803487.egg-info/entry_points.txt
TOPSIS_Akshit_101803487.egg-info/requires.txt
TOPSIS_Akshit_101803487.egg-info/top_level.txt
src/topsis.py