Metadata-Version: 2.1
Name: TOPSIS-Akshit-101803487
Version: 1.0.0
Summary: A Python package implementing TOPSIS technique.
Home-page: https://coe1316.ml
Author: Akshit Kumar
Author-email: akshitmittal912@gmail.com
License: MIT
Platform: UNKNOWN
Classifier: License :: OSI Approved :: MIT License
Classifier: Programming Language :: Python :: 3
Classifier: Programming Language :: Python :: 3.4
Classifier: Programming Language :: Python :: 3.5
Classifier: Programming Language :: Python :: 3.6
Classifier: Programming Language :: Python :: 3.7
